setup.py
XMLLayout.egg-info/PKG-INFO
XMLLayout.egg-info/SOURCES.txt
XMLLayout.egg-info/dependency_links.txt
XMLLayout.egg-info/not-zip-safe
XMLLayout.egg-info/top_level.txt
xmllayout/__init__.py
xmllayout/formatters.py
xmllayout/handlers.py
xmllayout/tests/__init__.py
xmllayout/tests/test_formatters.py