Metadata-Version: 1.0
Name: XMLLayout
Version: 1.0
Summary: Formats Python log messages as log4j XMLLayout XML
Home-page: http://pypi.python.org/pypi/XMLLayout
Author: Philip Jenvey
Author-email: pjenvey@groovie.org
License: BSD
Keywords: logging log4j
Platform: UNKNOWN
Classifier: Development Status :: 5 - Production/Stable
Classifier: Intended Audience :: Developers
Classifier: License :: OSI Approved :: BSD License
Classifier: Programming Language :: Python
Classifier: Programming Language :: Python :: 3
Classifier: Programming Language :: Python :: Implementation :: CPython
Classifier: Programming Language :: Python :: Implementation :: PyPy
Classifier: Programming Language :: Python :: Implementation :: Jython
Classifier: Topic :: System :: Logging
